llmvision/__init__.py
llmvision/__main__.py
llmvision/llm_tokenizers.py
llmvision/side_by_side.py
llmvision/tokenizer.py
llmvision-0.1.1.dist-info/METADATA
llmvision-0.1.1.dist-info/WHEEL
llmvision-0.1.1.dist-info/entry_points.txt
llmvision-0.1.1.dist-info/licenses/LICENSE
llmvision-0.1.1.dist-info/RECORD
