Metadata-Version: 2.4
Name: llmvision
Version: 0.1.1
Summary: Visualize how LLMs tokenize text
Project-URL: Homepage, https://github.com/alokbeniwal/llmvision
Project-URL: Documentation, https://github.com/alokbeniwal/llmvision#readme
Project-URL: Repository, https://github.com/alokbeniwal/llmvision
Project-URL: Issues, https://github.com/alokbeniwal/llmvision/issues
Author-email: Alok Singh <alokbeniwal@gmail.com>
License: MIT
License-File: LICENSE
Keywords: gpt,llm,nlp,tokenization,tokenizer,visualization
Classifier: Development Status :: 4 - Beta
Classifier: Intended Audience :: Developers
Classifier: Intended Audience :: Science/Research
Classifier: License :: OSI Approved :: MIT License
Classifier: Programming Language :: Python :: 3
Classifier: Programming Language :: Python :: 3.10
Classifier: Programming Language :: Python :: 3.11
Classifier: Programming Language :: Python :: 3.12
Classifier: Topic :: Scientific/Engineering :: Artificial Intelligence
Classifier: Topic :: Text Processing :: Linguistic
Requires-Python: >=3.10
Requires-Dist: regex>=2024.11.6
Requires-Dist: tiktoken>=0.8.0
